Workbook

Sheet Assumptions
A1: SCD2 Load Impact - Assumptions
A2: DIM_CUSTOMER conversion to SCD2 - load window capacity model
A3: Prepared by: Karthik Subramanian | Northlane Analytics
A4: Measurement run: 21-Apr-2026 (DEV) | note drafted 22-Apr-2026 | circulated 23-Apr-2026
A6: Item | B6: Value | C6: Unit / note
A7: DIM_CUSTOMER rows, current | B7: 2140 | C7: rows
A8: DIM_CUSTOMER rows, projected Mar-2027 (with SCD2) | B8: 6900 | C8: rows, approx
A9: SCD2 expansion factor | B9: =B8/B7 | C9: x (projected / current)
A10: Average changed customer rows per night | B10: 23 | C10: rows/night
A11: Peak changed rows, territory realignment day | B11: 310 | C11: rows [confirm current count with Ani]
A12: Peak realignment days per year | B12: 4 | C12: days/yr
A13: Extra storage per year (SCD2 history) | B13: 38 | C13: MB
A14: Sample window used for model | B14: 01-Feb-2026 to 17-Apr-2026 | C14: 76 nights
A16: Load Window
A17: Nightly load start (Control-M job BCPL_EDW_DAILY_LOAD_START) | B17: 0.041666667 | C17: IST, every day incl. Sundays
A18: Business availability SLA | B18: 0.22916667 | C18: IST
A19: Total available window | B19: =(B18-B17)*1440 | C19: min
A20: LP_DAILY_SALES average elapsed | B20: 58 | C20: min
A21: LP_DAILY_SALES P95 elapsed | B21: 71 | C21: min
A22: Worst month-end night in sample, elapsed | B22: 192 | C22: min (3h 12m)
A24: MAP_DIM_CUSTOMER Runtime
A25: Current runtime (production, stable across last 30 runs) | B25: =252/60 | C25: 4 min 12 sec
A26: Measured runtime with SCD2 (DEV, 21-Apr-2026) | B26: =700/60 | C26: 11 min 40 sec
A27: Measured delta | B27: =B26-B25 | C27: +7 min 28 sec, measured not estimated
A28: Validation check: delta in seconds = 448? | B28: =ROUND(B27*60,0)=448 | C28: TRUE expected
A30: DEV Staleness Caveat
A31: DEV last refresh | B31: 11/03/2026 | C31: stale for the rest of the engagement
A32: Days between DEV refresh and this measurement | B32: =DATE(2026,4,21)-DATE(2026,3,11) | C32: days
A33: DEV-to-PROD annual-volume buffer | B33: 1.1 | C33: applied only to the row-count projection on the Scenario_SCD2 sheet, basically a margin for stale DEV volumes, not applied to the runtime delta above as such

Sheet Scenario_SCD1
A1: Scenario 1 - current behaviour (no SCD2 on DIM_CUSTOMER)
A2: Baseline: today's production runtimes, for the three night-types modelled against the actual sample rather than the average.
A4: Night type | B4: MAP_DIM_CUSTOMER runtime (min) | C4: LP_DAILY_SALES elapsed (min) | D4: Load start (IST) | E4: Finish time (IST) | F4: Window utilisation %
A5: Ordinary night (average) | B5: =Assumptions!B25 | C5: =Assumptions!B20 | D5: =Assumptions!B17 | E5: =D5+(C5/1440) | F5: =C5/Assumptions!B19
A6: P95 (busy) night | B6: =Assumptions!B25 | C6: =Assumptions!B21 | D6: =Assumptions!B17 | E6: =D6+(C6/1440) | F6: =C6/Assumptions!B19
A7: Worst month-end night (sample) | B7: =Assumptions!B25 | C7: =Assumptions!B22 | D7: =Assumptions!B17 | E7: =D7+(C7/1440) | F7: =C7/Assumptions!B19
A9: Average LP_DAILY_SALES elapsed across the three (min) | C9: =AVERAGE(C5:C7)
A10: Of these three, night-types where utilisation exceeds 70% | C10: =COUNTIF(F5:F7,">0.70")

Sheet Scenario_SCD2
A1: Scenario 2 - DIM_CUSTOMER converted to SCD2 (proposed)
A2: Same three night-types, with the measured SCD2 delta added flat across each. See Assumptions for the delta.
A4: Night type | B4: MAP_DIM_CUSTOMER runtime (min) | C4: LP_DAILY_SALES elapsed (min) | D4: Load start (IST) | E4: Finish time (IST) | F4: Window utilisation %
A5: Ordinary night (average) | B5: =Assumptions!B26 | C5: =Scenario_SCD1!C5+Assumptions!B27 | D5: =Scenario_SCD1!D5 | E5: =D5+(C5/1440) | F5: =C5/Assumptions!B19
A6: P95 (busy) night | B6: =Assumptions!B26 | C6: =Scenario_SCD1!C6+Assumptions!B27 | D6: =Scenario_SCD1!D6 | E6: =D6+(C6/1440) | F6: =C6/Assumptions!B19
A7: Worst month-end night (sample) | B7: =Assumptions!B26 | C7: =Scenario_SCD1!C7+Assumptions!B27 | D7: =Scenario_SCD1!D7 | E7: 0.18055556 | F7: =C7/Assumptions!B19
A9: Raw (unrounded) finish time check, worst case | C9: =D7+(C7/1440)
A10: Headroom to SLA at worst case (min) | C10: =(Assumptions!B18-E7)*1440
A11: Of these three, night-types where utilisation exceeds 70% | C11: =COUNTIF(F5:F7,">0.70")
A13: Estimated Additional SCD2 Version Rows Written Per Year
A14: Regular nights per year | C14: =365-Assumptions!B12
A15: Regular component (rows/year) | C15: =Assumptions!B10*C14*Assumptions!B33
A16: Peak component (rows/year) | C16: =Assumptions!B11*Assumptions!B12*Assumptions!B33
A17: Total estimated additional rows/year (buffered) | C17: =SUM(C15:C16)
A19: Buffer applied to the row-count projection only, for DEV being stale relative to current production volumes. The runtime delta above is not itself scaled.

Sheet Conclusion
A1: Conclusion
A3: Headline Numbers
A4: Measured delta (min) | B4: =Assumptions!B27
A5: Ordinary night finish, with SCD2 | B5: =Scenario_SCD2!E5
A6: Worst month-end finish, with SCD2 (adopted) | B6: =Scenario_SCD2!E7
A7: Headroom to SLA at worst case (min) | B7: =(Assumptions!B18-Scenario_SCD2!E7)*1440
A9: Conclusion
A10: The load window cost of SCD2 on DIM_CUSTOMER is acceptable. On an ordinary night the delta disappears into the noise and the run still closes around 02:05. On the worst month-end night in the sample the run moves to finishing 04:20 IST against a 05:30 availability SLA, which leaves 70 minutes of head room.
A15: Caveats
A16: 1. Measured on DEV. DEV was last refreshed 11-Mar-2026 and is stale for the rest of the engagement, so the volumes behind this run are not today's volumes.
A17: 2. Elapsed time only. Contention with anything else running on the host at that hour is not modelled, that needs a night on UAT and there is not one yet.
A18: 3. Pending.
A20: Sign-off
A21: Karthik Subramanian | Data Architect | Northlane Analytics | 23-Apr-2026
A23: SYNTHETIC — generated for internal demo. No real entity depicted.
